data_formulator/__init__.py
data_formulator/__main__.py
data_formulator/agent_routes.py
data_formulator/app.py
data_formulator/db_manager.py
data_formulator/example_datasets_config.py
data_formulator/py_sandbox.py
data_formulator/tables_routes.py
data_formulator/agents/__init__.py
data_formulator/agents/agent_code_explanation.py
data_formulator/agents/agent_concept_derive.py
data_formulator/agents/agent_data_clean.py
data_formulator/agents/agent_data_clean_stream.py
data_formulator/agents/agent_data_load.py
data_formulator/agents/agent_exploration.py
data_formulator/agents/agent_interactive_explore.py
data_formulator/agents/agent_py_concept_derive.py
data_formulator/agents/agent_py_data_rec.py
data_formulator/agents/agent_py_data_transform.py
data_formulator/agents/agent_query_completion.py
data_formulator/agents/agent_report_gen.py
data_formulator/agents/agent_sort_data.py
data_formulator/agents/agent_sql_data_rec.py
data_formulator/agents/agent_sql_data_transform.py
data_formulator/agents/agent_utils.py
data_formulator/agents/client_utils.py
data_formulator/agents/web_utils.py
data_formulator/data_loader/__init__.py
data_formulator/data_loader/azure_blob_data_loader.py
data_formulator/data_loader/external_data_loader.py
data_formulator/data_loader/kusto_data_loader.py
data_formulator/data_loader/mssql_data_loader.py
data_formulator/data_loader/mysql_data_loader.py
data_formulator/data_loader/postgresql_data_loader.py
data_formulator/data_loader/s3_data_loader.py
data_formulator/dist/DataFormulator.js
data_formulator/dist/data-formulator-screenshot-v0.5.png
data_formulator/dist/data-formulator-screenshot-v0.5.webp
data_formulator/dist/data-formulator-screenshot.png
data_formulator/dist/df_gas_prices.json
data_formulator/dist/df_global_energy.json
data_formulator/dist/df_movies.json
data_formulator/dist/df_unemployment.json
data_formulator/dist/favicon.ico
data_formulator/dist/feature-agent-mode.mp4
data_formulator/dist/feature-extract-data.mp4
data_formulator-0.5.0.1.dist-info/licenses/LICENSE
data_formulator-0.5.0.1.dist-info/METADATA
data_formulator-0.5.0.1.dist-info/WHEEL
data_formulator-0.5.0.1.dist-info/entry_points.txt
data_formulator-0.5.0.1.dist-info/top_level.txt
data_formulator-0.5.0.1.dist-info/RECORD
