Metadata-Version: 2.4
Name: data_formulator
Version: 0.5.0.1
Summary: Data Formulator is research protoype data visualization tool powered by AI.
Author-email: Chenglong Wang <chenglong.wang@microsoft.com>, Dan Marshall <danmar@microsoft.com>
License-Expression: MIT
Project-URL: Homepage, https://github.com/microsoft/data-formulator
Project-URL: Repository, https://github.com/microsoft/data-formulator.git
Project-URL: Bug Tracker, https://github.com/microsoft/data-formulator/issues
Keywords: data visualization,LLM,AI
Classifier: Development Status :: 4 - Beta
Classifier: Programming Language :: Python
Requires-Python: >=3.12
License-File: LICENSE
Requires-Dist: jupyter
Requires-Dist: pandas
Requires-Dist: flask
Requires-Dist: flask-cors
Requires-Dist: openai
Requires-Dist: azure-identity
Requires-Dist: azure-kusto-data
Requires-Dist: azure-keyvault-secrets
Requires-Dist: azure-storage-blob
Requires-Dist: python-dotenv
Requires-Dist: vega_datasets
Requires-Dist: litellm
Requires-Dist: duckdb
Requires-Dist: pyodbc
Requires-Dist: numpy
Requires-Dist: vl-convert-python
Requires-Dist: boto3
Requires-Dist: backoff
Requires-Dist: beautifulsoup4
Requires-Dist: scikit-learn
Dynamic: license-file
